dragonlib/__init__.py
dragonlib/__main__.py
dragonlib/api.py
dragonlib/constants.py
dragonlib/CoCo/__init__.py
dragonlib/CoCo/basic_tokens.py
dragonlib/cli_app/__init__.py
dragonlib/cli_app/update_readme_history.py
dragonlib/cli_dev/__init__.py
dragonlib/cli_dev/code_style.py
dragonlib/cli_dev/packaging.py
dragonlib/cli_dev/testing.py
dragonlib/core/__init__.py
dragonlib/core/basic.py
dragonlib/core/basic_parser.py
dragonlib/core/binary_files.py
dragonlib/dragon32/__init__.py
dragonlib/dragon32/basic_tokens.py
dragonlib/dragon32/pygments_lexer.py
dragonlib/tests/AUTOLOAD.DWL
dragonlib/tests/__init__.py
dragonlib/tests/test_api.py
dragonlib/tests/test_base.py
dragonlib/tests/test_basic_parser.py
dragonlib/tests/test_binary_format.py
dragonlib/tests/test_doctests.py
dragonlib/tests/test_highlighting.py
dragonlib/tests/test_project_setup.py
dragonlib/tests/test_readme.py
dragonlib/tests/test_readme_history.py
dragonlib/tests/testdata.py
dragonlib/utils/__init__.py
dragonlib/utils/auto_shift.py
dragonlib/utils/byte_word_values.py
dragonlib/utils/iter_utils.py
dragonlib/utils/logging_utils.py
dragonlib-0.2.0.dist-info/AUTHORS
dragonlib-0.2.0.dist-info/LICENSE
dragonlib-0.2.0.dist-info/METADATA
dragonlib-0.2.0.dist-info/WHEEL
dragonlib-0.2.0.dist-info/entry_points.txt
dragonlib-0.2.0.dist-info/top_level.txt
dragonlib-0.2.0.dist-info/RECORD
